README.rst
setup.py
giza/__init__.py
giza/cmdline.py
giza/corp.py
giza/deploy.py
giza/github.py
giza/includes.py
giza/inheritance.py
giza.egg-info/PKG-INFO
giza.egg-info/SOURCES.txt
giza.egg-info/dependency_links.txt
giza.egg-info/entry_points.txt
giza.egg-info/requires.txt
giza.egg-info/top_level.txt
giza/config/__init__.py
giza/config/assets.py
giza/config/code_review.py
giza/config/content.py
giza/config/credentials.py
giza/config/deploy.py
giza/config/error.py
giza/config/git.py
giza/config/github.py
giza/config/helper.py
giza/config/images.py
giza/config/intersphinx.py
giza/config/jeerah.py
giza/config/main.py
giza/config/manpage.py
giza/config/migrations.py
giza/config/paths.py
giza/config/pdfs.py
giza/config/project.py
giza/config/redirects.py
giza/config/replacements.py
giza/config/runtime.py
giza/config/sphinx_config.py
giza/config/sphinx_local.py
giza/config/system.py
giza/config/test.py
giza/config/version.py
giza/content/__init__.py
giza/content/assets.py
giza/content/dependencies.py
giza/content/hash.py
giza/content/helper.py
giza/content/intersphinx.py
giza/content/links.py
giza/content/migrations.py
giza/content/redirects.py
giza/content/replacements.py
giza/content/robots.py
giza/content/source.py
giza/content/sphinx.py
giza/content/apiargs/__init__.py
giza/content/apiargs/inheritance.py
giza/content/apiargs/models.py
giza/content/apiargs/tasks.py
giza/content/apiargs/views.py
giza/content/changelog/__init__.py
giza/content/changelog/tasks.py
giza/content/changelog/views.py
giza/content/examples/__init__.py
giza/content/examples/inheritance.py
giza/content/examples/models.py
giza/content/examples/tasks.py
giza/content/examples/views.py
giza/content/extract/__init__.py
giza/content/extract/inheritance.py
giza/content/extract/models.py
giza/content/extract/tasks.py
giza/content/extract/views.py
giza/content/glossary/__init__.py
giza/content/glossary/inheritance.py
giza/content/glossary/models.py
giza/content/glossary/tasks.py
giza/content/glossary/views.py
giza/content/images/__init__.py
giza/content/images/tasks.py
giza/content/images/views.py
giza/content/options/__init__.py
giza/content/options/inheritance.py
