Metadata-Version: 1.1
Name: giza
Version: 0.5.18
Summary: Sphinx Documentation Build Automation
Home-page: http://github.com/mongodb/docs-tools.git
Author: tychoish
Author-email: sam@tychoish.com
License: Apache 2.0
Platform: UNKNOWN
Classifier: Environment :: Console
Classifier: Intended Audience :: Developers
Classifier: Topic :: Documentation
Classifier: Topic :: Software Development :: Testing
Classifier: Programming Language :: Python
Classifier: Programming Language :: Python :: 2
Classifier: License :: OSI Approved :: Apache Software License
